CalTechCal/analyse_error.m
CalTechCal/apply_distortion.m
CalTechCal/check_active_images.m
CalTechCal/comp_distortion_oulu.m
CalTechCal/comp_error_calib.m
CalTechCal/comp_ext_calib.m
CalTechCal/compute_extrinsic_init.m
CalTechCal/compute_extrinsic_refine.m
CalTechCal/export_calib_data.m
CalTechCal/extract_parameters.m
CalTechCal/ginput3.m
CalTechCal/go_calib_optim_iter.m
CalTechCal/gorad.m
CalTechCal/goradf.m
CalTechCal/normalize.m
CalTechCal/preparedata.m
CalTechCal/project_points2.m
CalTechCal/quiver.m
CalTechCal/rigid_motion.m
CalTechCal/rodrigues.m
CalTechCal/visualize_distortions.m
CommonCfgAndIO/ConvertOldConfigToNew.m
CommonCfgAndIO/configdata.m
CommonCfgAndIO/expname.m
CommonCfgAndIO/loaddata.m
CommonCfgAndIO/oldexperiments.m
CommonCfgAndIO/read_configuration.m
CommonCfgAndIO/read_generic_configuration.m
MultiCamSelfCal/gocal.m
MultiCamSelfCal/showpoints.m
MultiCamSelfCal/BlueCLocal/align_existing_camera_centers.m
MultiCamSelfCal/BlueCLocal/bluechoengg.m
MultiCamSelfCal/BlueCLocal/bluecrz.m
MultiCamSelfCal/BlueCLocal/flydra.m
MultiCamSelfCal/BlueCLocal/humdra.m
MultiCamSelfCal/BlueCLocal/mamarama.m
MultiCamSelfCal/BlueCLocal/strawlab_test.m
MultiCamSelfCal/CoreFunctions/align3d.m
MultiCamSelfCal/CoreFunctions/estimateLambda.m
MultiCamSelfCal/CoreFunctions/estimatePX.m
MultiCamSelfCal/CoreFunctions/estsimt.m
MultiCamSelfCal/CoreFunctions/euclidize.m
MultiCamSelfCal/CoreFunctions/findinl.m
MultiCamSelfCal/CoreFunctions/findoutl.m
MultiCamSelfCal/CoreFunctions/reprerror.m
MultiCamSelfCal/CoreFunctions/rq.m
MultiCamSelfCal/CoreFunctions/selfcalib.m
MultiCamSelfCal/FindingPoints/getpoint.m
MultiCamSelfCal/FindingPoints/im2imstat.m
MultiCamSelfCal/FindingPoints/im2points.m
MultiCamSelfCal/FindingPoints/mycorr2.m
MultiCamSelfCal/LocalAlignments/erlangen.m
MultiCamSelfCal/LocalAlignments/g9.m
MultiCamSelfCal/LocalAlignments/joinoscars.m
MultiCamSelfCal/LocalAlignments/nfi2r.m
MultiCamSelfCal/LocalAlignments/planarcams.m
MultiCamSelfCal/LocalAlignments/planarmove.m
multicamselfcal-0.3.0.dist-info/METADATA
multicamselfcal-0.3.0.dist-info/WHEEL
multicamselfcal-0.3.0.dist-info/top_level.txt
multicamselfcal-0.3.0.dist-info/RECORD
