Metadata-Version: 2.1
Name: multicamselfcal
Version: 0.3.0
Summary: wrapper for the Octave/Matlab multicamselfcal library
Author: John Stowers
Maintainer-email: Andrew Straw <strawman@astraw.com>
Project-URL: homepage, https://github.com/strawlab/multicamselfcal
Requires-Python: >=3.8
Requires-Dist: numpy
Requires-Dist: PyYAML
Requires-Dist: importlib-resources >=6
